justdo/__init__.py
justdo/ai.py
justdo/api.py
justdo/cli.py
justdo/emotion.py
justdo/manager.py
justdo/models.py
justdo/prompts.py
justdo/trash.py
justdo/user_profile.py
justdo/static/index.html
justdo-0.1.3.dist-info/METADATA
justdo-0.1.3.dist-info/WHEEL
justdo-0.1.3.dist-info/entry_points.txt
justdo-0.1.3.dist-info/top_level.txt
justdo-0.1.3.dist-info/RECORD
