Metadata-Version: 2.4
Name: justdo
Version: 0.1.3
Summary: Just do it! - 一个简单的命令行待办事项工具
Author: gqy20
License-Expression: MIT
Project-URL: Homepage, https://github.com/gqy20/justdo
Project-URL: Repository, https://github.com/gqy20/justdo
Project-URL: Documentation, http://home.gqy20.top/justdo/
Project-URL: Issue Tracker, https://github.com/gqy20/justdo/issues
Keywords: todo,cli,task,productivity,doit,priority
Classifier: Development Status :: 4 - Beta
Classifier: Intended Audience :: Developers
Classifier: Intended Audience :: End Users/Desktop
Classifier: Programming Language :: Python :: 3
Classifier: Programming Language :: Python :: 3.8
Classifier: Programming Language :: Python :: 3.9
Classifier: Programming Language :: Python :: 3.10
Classifier: Programming Language :: Python :: 3.11
Classifier: Programming Language :: Python :: 3.12
Classifier: Topic :: Utilities
Classifier: Topic :: Office/Business
Classifier: Environment :: Console
Requires-Python: >=3.8
Provides-Extra: dev
Requires-Dist: pytest>=7.0.0; extra == "dev"
Provides-Extra: ai
Requires-Dist: openai>=1.0.0; extra == "ai"
Provides-Extra: web
Requires-Dist: fastapi>=0.100.0; extra == "web"
Requires-Dist: uvicorn>=0.23.0; extra == "web"
